sms_devino
